odoo/addons/stock_orderpoint_manual_procurement/README.rst
odoo/addons/stock_orderpoint_manual_procurement/__init__.py
odoo/addons/stock_orderpoint_manual_procurement/__manifest__.py
odoo/addons/stock_orderpoint_manual_procurement/demo/product.xml
odoo/addons/stock_orderpoint_manual_procurement/i18n/it.po
odoo/addons/stock_orderpoint_manual_procurement/i18n/stock_orderpoint_manual_procurement.pot
odoo/addons/stock_orderpoint_manual_procurement/i18n/zh_CN.po
odoo/addons/stock_orderpoint_manual_procurement/models/__init__.py
odoo/addons/stock_orderpoint_manual_procurement/models/stock_warehouse_orderpoint.py
odoo/addons/stock_orderpoint_manual_procurement/readme/CONFIGURE.md
odoo/addons/stock_orderpoint_manual_procurement/readme/CONTRIBUTORS.md
odoo/addons/stock_orderpoint_manual_procurement/readme/CREDITS.md
odoo/addons/stock_orderpoint_manual_procurement/readme/DESCRIPTION.md
odoo/addons/stock_orderpoint_manual_procurement/readme/USAGE.md
odoo/addons/stock_orderpoint_manual_procurement/security/ir.model.access.csv
odoo/addons/stock_orderpoint_manual_procurement/security/stock_orderpoint_manual_procurement_security.xml
odoo/addons/stock_orderpoint_manual_procurement/static/description/icon.png
odoo/addons/stock_orderpoint_manual_procurement/static/description/index.html
odoo/addons/stock_orderpoint_manual_procurement/static/src/views/stock_orderpoint_list_view.esm.js
odoo/addons/stock_orderpoint_manual_procurement/static/src/views/stock_orderpoint_list_view.xml
odoo/addons/stock_orderpoint_manual_procurement/tests/__init__.py
odoo/addons/stock_orderpoint_manual_procurement/tests/test_stock_orderpoint_manual_procurement.py
odoo/addons/stock_orderpoint_manual_procurement/views/stock_warehouse_orderpoint_view.xml
odoo/addons/stock_orderpoint_manual_procurement/wizards/__init__.py
odoo/addons/stock_orderpoint_manual_procurement/wizards/make_procurement_orderpoint.py
odoo/addons/stock_orderpoint_manual_procurement/wizards/make_procurement_orderpoint_view.xml
odoo_addon_stock_orderpoint_manual_procurement-18.0.1.0.0.2.dist-info/METADATA
odoo_addon_stock_orderpoint_manual_procurement-18.0.1.0.0.2.dist-info/WHEEL
odoo_addon_stock_orderpoint_manual_procurement-18.0.1.0.0.2.dist-info/top_level.txt
odoo_addon_stock_orderpoint_manual_procurement-18.0.1.0.0.2.dist-info/RECORD
